{"_default": {"1": {"name": "\u5317\u4eac", "code": "010000"}, "2": {"name": "\u4e1c\u57ce\u533a", "code": "010100"}, "3": {"name": "\u897f\u57ce\u533a", "code": "010200"}, "4": {"name": "\u671d\u9633\u533a", "code": "010500"}, "5": {"name": "\u4e30\u53f0\u533a", "code": "010600"}, "6": {"name": "\u77f3\u666f\u5c71\u533a", "code": "010700"}, "7": {"name": "\u6d77\u6dc0\u533a", "code": "010800"}, "8": {"name": "\u95e8\u5934\u6c9f\u533a", "code": "010900"}, "9": {"name": "\u623f\u5c71\u533a", "code": "011000"}, "10": {"name": "\u901a\u5dde\u533a", "code": "011100"}, "11": {"name": "\u987a\u4e49\u533a", "code": "011200"}, "12": {"name": "\u660c\u5e73\u533a", "code": "011300"}, "13": {"name": "\u5927\u5174\u533a", "code": "011400"}, "14": {"name": "\u6000\u67d4\u533a", "code": "011500"}, "15": {"name": "\u5e73\u8c37\u533a", "code": "011600"}, "16": {"name": "\u5bc6\u4e91\u533a", "code": "011700"}, "17": {"name": "\u5ef6\u5e86\u533a", "code": "011800"}, "18": {"name": "\u4e0a\u6d77", "code": "020000"}, "19": {"name": "\u9ec4\u6d66\u533a", "code": "020100"}, "20": {"name": "\u5f90\u6c47\u533a", "code": "020300"}, "21": {"name": "\u957f\u5b81\u533a", "code": "020400"}, "22": {"name": "\u9759\u5b89\u533a", "code": "020500"}, "23": {"name": "\u666e\u9640\u533a", "code": "020600"}, "24": {"name": "\u8679\u53e3\u533a", "code": "020800"}, "25": {"name": "\u6768\u6d66\u533a", "code": "020900"}, "26": {"name": "\u6d66\u4e1c\u65b0\u533a", "code": "021000"}, "27": {"name": "\u95f5\u884c\u533a", "code": "021100"}, "28": {"name": "\u5b9d\u5c71\u533a", "code": "021200"}, "29": {"name": "\u5609\u5b9a\u533a", "code": "021300"}, "30": {"name": "\u91d1\u5c71\u533a", "code": "021400"}, "31": {"name": "\u677e\u6c5f\u533a", "code": "021500"}, "32": {"name": "\u9752\u6d66\u533a", "code": "021600"}, "33": {"name": "\u5949\u8d24\u533a", "code": "021800"}, "34": {"name": "\u5d07\u660e\u533a", "code": "021900"}, "35": {"name": "\u5e7f\u4e1c\u7701", "code": "030000"}, "36": {"name": "\u5e7f\u5dde", "code": "030200"}, "37": {"name": "\u8d8a\u79c0\u533a", "code": "030201"}, "38": {"name": "\u8354\u6e7e\u533a", "code": "030202"}, "39": {"name": "\u6d77\u73e0\u533a", "code": "030203"}, "40": {"name": "\u5929\u6cb3\u533a", "code": "030204"}, "41": {"name": "\u767d\u4e91\u533a", "code": "030205"}, "42": {"name": "\u9ec4\u57d4\u533a", "code": "030206"}, "43": {"name": "\u756a\u79ba\u533a", "code": "030207"}, "44": {"name": "\u82b1\u90fd\u533a", "code": "030208"}, "45": {"name": "\u5357\u6c99\u533a", "code": "030209"}, "46": {"name": "\u589e\u57ce", "code": "030211"}, "47": {"name": "\u4ece\u5316", "code": "030212"}, "48": {"name": "\u60e0\u5dde", "code": "030300"}, "49": {"name": "\u6c55\u5934", "code": "030400"}, "50": {"name": "\u73e0\u6d77", "code": "030500"}, "51": {"name": "\u9999\u6d32\u533a", "code": "030501"}, "52": {"name": "\u6597\u95e8\u533a", "code": "030502"}, "53": {"name": "\u91d1\u6e7e\u533a", "code": "030503"}, "54": {"name": "\u6a2a\u7434\u65b0\u533a", "code": "030504"}, "55": {"name": "\u9ad8\u680f\u6e2f\u7ecf\u6d4e\u533a", "code": "030505"}, "56": {"name": "\u73e0\u6d77\u9ad8\u65b0\u533a", "code": "030506"}, "57": {"name": "\u73e0\u6d77\u4fdd\u7a0e\u533a", "code": "030507"}, "58": {"name": "\u4e07\u5c71\u6d77\u6d0b\u5f00\u53d1\u8bd5\u9a8c\u533a", "code": "030508"}, "59": {"name": "\u4f5b\u5c71", "code": "030600"}, "60": {"name": "\u7985\u57ce\u533a", "code": "030601"}, "61": {"name": "\u987a\u5fb7\u533a", "code": "030602"}, "62": {"name": "\u5357\u6d77\u533a", "code": "030603"}, "63": {"name": "\u4e09\u6c34\u533a", "code": "030604"}, "64": {"name": "\u9ad8\u660e\u533a", "code": "030605"}, "65": {"name": "\u4e2d\u5c71", "code": "030700"}, "66": {"name": "\u4e1c\u839e", "code": "030800"}, "67": {"name": "\u839e\u57ce\u533a", "code": "030801"}, "68": {"name": "\u5357\u57ce\u533a", "code": "030802"}, "69": {"name": "\u4e1c\u57ce\u533a", "code": "030803"}, "70": {"name": "\u4e07\u6c5f\u533a", "code": "030804"}, "71": {"name": "\u77f3\u78a3\u9547", "code": "030805"}, "72": {"name": "\u77f3\u9f99\u9547", "code": "030806"}, "73": {"name": "\u8336\u5c71\u9547", "code": "030807"}, "74": {"name": "\u77f3\u6392\u9547", "code": "030808"}, "75": {"name": "\u4f01\u77f3\u9547", "code": "030809"}, "76": {"name": "\u6a2a\u6ca5\u9547", "code": "030810"}, "77": {"name": "\u6865\u5934\u9547", "code": "030811"}, "78": {"name": "\u8c22\u5c97\u9547", "code": "030812"}, "79": {"name": "\u4e1c\u5751\u9547", "code": "030813"}, "80": {"name": "\u5e38\u5e73\u9547", "code": "030814"}, "81": {"name": "\u5bee\u6b65\u9547", "code": "030815"}, "82": {"name": "\u5927\u6717\u9547", "code": "030816"}, "83": {"name": "\u9ebb\u6d8c\u9547", "code": "030817"}, "84": {"name": "\u4e2d\u5802\u9547", "code": "030818"}, "85": {"name": "\u9ad8\u58a9", "code": "030819"}, "86": {"name": "\u6a1f\u6728\u5934\u9547", "code": "030820"}, "87": {"name": "\u5927\u5cad\u5c71\u9547", "code": "030821"}, "88": {"name": "\u671b\u725b\u58a9\u9547", "code": "030822"}, "89": {"name": "\u9ec4\u6c5f\u9547", "code": "030823"}, "90": {"name": "\u6d2a\u6885\u9547", "code": "030824"}, "91": {"name": "\u6e05\u6eaa\u9547", "code": "030825"}, "92": {"name": "\u6c99\u7530\u9547", "code": "030826"}, "93": {"name": "\u9053\u86d8", "code": "030827"}, "94": {"name": "\u5858\u53a6\u9547", "code": "030828"}, "95": {"name": "\u864e\u95e8\u9547", "code": "030829"}, "96": {"name": "\u539a\u8857\u9547", "code": "030830"}, "97": {"name": "\u51e4\u5c97\u9547", "code": "030831"}, "98": {"name": "\u957f\u5b89\u9547", "code": "030832"}, "99": {"name": "\u677e\u5c71\u6e56\u533a", "code": "030833"}, "100": {"name": "\u97f6\u5173", "code": "031400"}, "101": {"name": "\u6c5f\u95e8", "code": "031500"}, "102": {"name": "\u6e5b\u6c5f", "code": "031700"}, "103": {"name": "\u8087\u5e86", "code": "031800"}, "104": {"name": "\u6e05\u8fdc", "code": "031900"}, "105": {"name": "\u6f6e\u5dde", "code": "032000"}, "106": {"name": "\u6cb3\u6e90", "code": "032100"}, "107": {"name": "\u63ed\u9633", "code": "032200"}, "108": {"name": "\u8302\u540d", "code": "032300"}, "109": {"name": "\u6c55\u5c3e", "code": "032400"}, "110": {"name": "\u6885\u5dde", "code": "032600"}, "111": {"name": "\u5f00\u5e73", "code": "032700"}, "112": {"name": "\u9633\u6c5f", "code": "032800"}, "113": {"name": "\u4e91\u6d6e", "code": "032900"}, "114": {"name": "\u6df1\u5733", "code": "040000"}, "115": {"name": "\u798f\u7530\u533a", "code": "040100"}, "116": {"name": "\u7f57\u6e56\u533a", "code": "040200"}, "117": {"name": "\u5357\u5c71\u533a", "code": "040300"}, "118": {"name": "\u76d0\u7530\u533a", "code": "040400"}, "119": {"name": "\u5b9d\u5b89\u533a", "code": "040500"}, "120": {"name": "\u9f99\u5c97\u533a", "code": "040600"}, "121": {"name": "\u5149\u660e\u65b0\u533a", "code": "040700"}, "122": {"name": "\u576a\u5c71\u533a", "code": "040800"}, "123": {"name": "\u5927\u9e4f\u65b0\u533a", "code": "040900"}, "124": {"name": "\u9f99\u534e\u65b0\u533a", "code": "041000"}, "125": {"name": "\u5929\u6d25", "code": "050000"}, "126": {"name": "\u548c\u5e73\u533a", "code": "050100"}, "127": {"name": "\u6cb3\u4e1c\u533a", "code": "050200"}, "128": {"name": "\u6cb3\u897f\u533a", "code": "050300"}, "129": {"name": "\u5357\u5f00\u533a", "code": "050400"}, "130": {"name": "\u6cb3\u5317\u533a", "code": "050500"}, "131": {"name": "\u7ea2\u6865\u533a", "code": "050600"}, "132": {"name": "\u4e1c\u4e3d\u533a", "code": "050700"}, "133": {"name": "\u897f\u9752\u533a", "code": "050800"}, "134": {"name": "\u6d25\u5357\u533a", "code": "050900"}, "135": {"name": "\u5317\u8fb0\u533a", "code": "051000"}, "136": {"name": "\u6b66\u6e05\u533a", "code": "051100"}, "137": {"name": "\u5b9d\u577b\u533a", "code": "051200"}, "138": {"name": "\u6ee8\u6d77\u65b0\u533a", "code": "051300"}, "139": {"name": "\u5b81\u6cb3\u533a", "code": "051400"}, "140": {"name": "\u9759\u6d77\u533a", "code": "051500"}, "141": {"name": "\u84df\u5dde\u533a", "code": "051600"}, "142": {"name": "\u91cd\u5e86", "code": "060000"}, "143": {"name": "\u6e1d\u4e2d\u533a", "code": "060100"}, "144": {"name": "\u5927\u6e21\u53e3\u533a", "code": "060200"}, "145": {"name": "\u6c5f\u5317\u533a", "code": "060300"}, "146": {"name": "\u6c99\u576a\u575d\u533a", "code": "060400"}, "147": {"name": "\u5408\u5ddd\u533a", "code": "060600"}, "148": {"name": "\u6e1d\u5317\u533a", "code": "060700"}, "149": {"name": "\u6c38\u5ddd\u533a", "code": "060800"}, "150": {"name": "\u5df4\u5357\u533a", "code": "060900"}, "151": {"name": "\u5357\u5ddd\u533a", "code": "061000"}, "152": {"name": "\u4e5d\u9f99\u5761\u533a", "code": "061100"}, "153": {"name": "\u4e07\u5dde\u533a", "code": "061200"}, "154": {"name": "\u6daa\u9675\u533a", "code": "061300"}, "155": {"name": "\u9ed4\u6c5f\u533a", "code": "061400"}, "156": {"name": "\u5357\u5cb8\u533a", "code": "061500"}, "157": {"name": "\u5317\u789a\u533a", "code": "061600"}, "158": {"name": "\u957f\u5bff\u533a", "code": "061700"}, "159": {"name": "\u6c5f\u6d25\u533a", "code": "061900"}, "160": {"name": "\u7da6\u6c5f\u533a", "code": "062000"}, "161": {"name": "\u6f7c\u5357\u533a", "code": "062100"}, "162": {"name": "\u94dc\u6881\u533a", "code": "062200"}, "163": {"name": "\u5927\u8db3\u533a", "code": "062300"}, "164": {"name": "\u8363\u660c\u533a", "code": "062400"}, "165": {"name": "\u74a7\u5c71\u533a", "code": "062500"}, "166": {"name": "\u57ab\u6c5f\u53bf", "code": "062600"}, "167": {"name": "\u4e30\u90fd\u53bf", "code": "062700"}, "168": {"name": "\u5fe0\u53bf", "code": "062800"}, "169": {"name": "\u77f3\u67f1\u53bf", "code": "062900"}, "170": {"name": "\u57ce\u53e3\u53bf", "code": "063000"}, "171": {"name": "\u5f6d\u6c34\u53bf", "code": "063100"}, "172": {"name": "\u6881\u5e73\u533a", "code": "063200"}, "173": {"name": "\u9149\u9633\u53bf", "code": "063300"}, "174": {"name": "\u5f00\u5dde\u533a", "code": "063400"}, "175": {"name": "\u79c0\u5c71\u53bf", "code": "063500"}, "176": {"name": "\u5deb\u6eaa\u53bf", "code": "063600"}, "177": {"name": "\u5deb\u5c71\u53bf", "code": "063700"}, "178": {"name": "\u5949\u8282\u53bf", "code": "063800"}, "179": {"name": "\u6b66\u9686\u533a", "code": "063900"}, "180": {"name": "\u4e91\u9633\u53bf", "code": "064000"}, "181": {"name": "\u6c5f\u82cf\u7701", "code": "070000"}, "182": {"name": "\u5357\u4eac", "code": "070200"}, "183": {"name": "\u7384\u6b66\u533a", "code": "070201"}, "184": {"name": "\u79e6\u6dee\u533a", "code": "070203"}, "185": {"name": "\u5efa\u90ba\u533a", "code": "070204"}, "186": {"name": "\u9f13\u697c\u533a", "code": "070205"}, "187": {"name": "\u6d66\u53e3\u533a", "code": "070207"}, "188": {"name": "\u516d\u5408\u533a", "code": "070208"}, "189": {"name": "\u6816\u971e\u533a", "code": "070209"}, "190": {"name": "\u96e8\u82b1\u53f0\u533a", "code": "070210"}, "191": {"name": "\u6c5f\u5b81\u533a", "code": "070211"}, "192": {"name": "\u6ea7\u6c34\u533a", "code": "070212"}, "193": {"name": "\u9ad8\u6df3\u533a", "code": "070213"}, "194": {"name": "\u82cf\u5dde", "code": "070300"}, "195": {"name": "\u59d1\u82cf\u533a", "code": "070301"}, "196": {"name": "\u5434\u4e2d\u533a", "code": "070303"}, "197": {"name": "\u76f8\u57ce\u533a", "code": "070304"}, "198": {"name": "\u5434\u6c5f\u533a", "code": "070305"}, "199": {"name": "\u5de5\u4e1a\u56ed\u533a", "code": "070306"}, "200": {"name": "\u9ad8\u65b0\u533a", "code": "070307"}, "201": {"name": "\u65e0\u9521", "code": "070400"}, "202": {"name": "\u6881\u6eaa\u533a", "code": "070401"}, "203": {"name": "\u6ee8\u6e56\u533a", "code": "070404"}, "204": {"name": "\u65e0\u9521\u65b0\u533a", "code": "070405"}, "205": {"name": "\u60e0\u5c71\u533a", "code": "070406"}, "206": {"name": "\u9521\u5c71\u533a", "code": "070407"}, "207": {"name": "\u5b9c\u5174\u5e02", "code": "070408"}, "208": {"name": "\u6c5f\u9634\u5e02", "code": "070409"}, "209": {"name": "\u5e38\u5dde", "code": "070500"}, "210": {"name": "\u5929\u5b81\u533a", "code": "070501"}, "211": {"name": "\u949f\u697c\u533a", "code": "070502"}, "212": {"name": "\u65b0\u5317\u533a", "code": "070504"}, "213": {"name": "\u6b66\u8fdb\u533a", "code": "070505"}, "214": {"name": "\u91d1\u575b\u533a", "code": "070506"}, "215": {"name": "\u6ea7\u9633\u5e02", "code": "070507"}, "216": {"name": "\u6606\u5c71", "code": "070600"}, "217": {"name": "\u5e38\u719f", "code": "070700"}, "218": {"name": "\u626c\u5dde", "code": "070800"}, "219": {"name": "\u5357\u901a", "code": "070900"}, "220": {"name": "\u9547\u6c5f", "code": "071000"}, "221": {"name": "\u5f90\u5dde", "code": "071100"}, "222": {"name": "\u8fde\u4e91\u6e2f", "code": "071200"}, "223": {"name": "\u76d0\u57ce", "code": "071300"}, "224": {"name": "\u5f20\u5bb6\u6e2f", "code": "071400"}, "225": {"name": "\u592a\u4ed3", "code": "071600"}, "226": {"name": "\u6cf0\u5dde", "code": "071800"}, "227": {"name": "\u6dee\u5b89", "code": "071900"}, "228": {"name": "\u5bbf\u8fc1", "code": "072000"}, "229": {"name": "\u4e39\u9633", "code": "072100"}, "230": {"name": "\u6cf0\u5174", "code": "072300"}, "231": {"name": "\u9756\u6c5f", "code": "072500"}, "232": {"name": "\u6d59\u6c5f\u7701", "code": "080000"}, "233": {"name": "\u676d\u5dde", "code": "080200"}, "234": {"name": "\u62f1\u5885\u533a", "code": "080201"}, "235": {"name": "\u4e0a\u57ce\u533a", "code": "080202"}, "236": {"name": "\u4e0b\u57ce\u533a", "code": "080203"}, "237": {"name": "\u6c5f\u5e72\u533a", "code": "080204"}, "238": {"name": "\u897f\u6e56\u533a", "code": "080205"}, "239": {"name": "\u6ee8\u6c5f\u533a", "code": "080206"}, "240": {"name": "\u4f59\u676d\u533a", "code": "080207"}, "241": {"name": "\u8427\u5c71\u533a", "code": "080208"}, "242": {"name": "\u4e34\u5b89\u533a", "code": "080209"}, "243": {"name": "\u5bcc\u9633\u533a", "code": "080210"}, "244": {"name": "\u5efa\u5fb7\u5e02", "code": "080211"}, "245": {"name": "\u6850\u5e90\u53bf", "code": "080212"}, "246": {"name": "\u6df3\u5b89\u53bf", "code": "080213"}, "247": {"name": "\u5b81\u6ce2", "code": "080300"}, "248": {"name": "\u6d77\u66d9\u533a", "code": "080301"}, "249": {"name": "\u6c5f\u5317\u533a", "code": "080303"}, "250": {"name": "\u5317\u4ed1\u533a", "code": "080304"}, "251": {"name": "\u9547\u6d77\u533a", "code": "080305"}, "252": {"name": "\u911e\u5dde\u533a", "code": "080306"}, "253": {"name": "\u6148\u6eaa\u5e02", "code": "080307"}, "254": {"name": "\u4f59\u59da\u5e02", "code": "080308"}, "255": {"name": "\u5949\u5316\u533a", "code": "080309"}, "256": {"name": "\u5b81\u6d77\u53bf", "code": "080310"}, "257": {"name": "\u8c61\u5c71\u53bf", "code": "080311"}, "258": {"name": "\u9ad8\u65b0\u533a", "code": "080312"}, "259": {"name": "\u6e29\u5dde", "code": "080400"}, "260": {"name": "\u7ecd\u5174", "code": "080500"}, "261": {"name": "\u91d1\u534e", "code": "080600"}, "262": {"name": "\u5609\u5174", "code": "080700"}, "263": {"name": "\u53f0\u5dde", "code": "080800"}, "264": {"name": "\u6e56\u5dde", "code": "080900"}, "265": {"name": "\u4e3d\u6c34", "code": "081000"}, "266": {"name": "\u821f\u5c71", "code": "081100"}, "267": {"name": "\u8862\u5dde", "code": "081200"}, "268": {"name": "\u4e49\u4e4c", "code": "081400"}, "269": {"name": "\u6d77\u5b81", "code": "081600"}, "270": {"name": "\u56db\u5ddd\u7701", "code": "090000"}, "271": {"name": "\u6210\u90fd", "code": "090200"}, "272": {"name": "\u9752\u7f8a\u533a", "code": "090201"}, "273": {"name": "\u9526\u6c5f\u533a", "code": "090202"}, "274": {"name": "\u91d1\u725b\u533a", "code": "090203"}, "275": {"name": "\u6b66\u4faf\u533a", "code": "090204"}, "276": {"name": "\u6210\u534e\u533a", "code": "090205"}, "277": {"name": "\u9f99\u6cc9\u9a7f\u533a", "code": "090206"}, "278": {"name": "\u9752\u767d\u6c5f\u533a", "code": "090207"}, "279": {"name": "\u65b0\u90fd\u533a", "code": "090208"}, "280": {"name": "\u6e29\u6c5f\u533a", "code": "090209"}, "281": {"name": "\u90fd\u6c5f\u5830\u5e02", "code": "090210"}, "282": {"name": "\u5f6d\u5dde\u5e02", "code": "090211"}, "283": {"name": "\u909b\u5d03\u5e02", "code": "090212"}, "284": {"name": "\u5d07\u5dde\u5e02", "code": "090213"}, "285": {"name": "\u91d1\u5802\u53bf", "code": "090214"}, "286": {"name": "\u53cc\u6d41\u533a", "code": "090215"}, "287": {"name": "\u90eb\u90fd\u533a", "code": "090216"}, "288": {"name": "\u5927\u9091\u53bf", "code": "090217"}, "289": {"name": "\u84b2\u6c5f\u53bf", "code": "090218"}, "290": {"name": "\u65b0\u6d25\u53bf", "code": "090219"}, "291": {"name": "\u9ad8\u65b0\u533a", "code": "090220"}, "292": {"name": "\u7b80\u9633\u5e02", "code": "090221"}, "293": {"name": "\u7ef5\u9633", "code": "090300"}, "294": {"name": "\u4e50\u5c71", "code": "090400"}, "295": {"name": "\u6cf8\u5dde", "code": "090500"}, "296": {"name": "\u5fb7\u9633", "code": "090600"}, "297": {"name": "\u5b9c\u5bbe", "code": "090700"}, "298": {"name": "\u81ea\u8d21", "code": "090800"}, "299": {"name": "\u5185\u6c5f", "code": "090900"}, "300": {"name": "\u6500\u679d\u82b1", "code": "091000"}, "301": {"name": "\u5357\u5145", "code": "091100"}, "302": {"name": "\u7709\u5c71", "code": "091200"}, "303": {"name": "\u5e7f\u5b89", "code": "091300"}, "304": {"name": "\u8d44\u9633", "code": "091400"}, "305": {"name": "\u9042\u5b81", "code": "091500"}, "306": {"name": "\u5e7f\u5143", "code": "091600"}, "307": {"name": "\u8fbe\u5dde", "code": "091700"}, "308": {"name": "\u96c5\u5b89", "code": "091800"}, "309": {"name": "\u897f\u660c", "code": "091900"}, "310": {"name": "\u5df4\u4e2d", "code": "092000"}, "311": {"name": "\u7518\u5b5c", "code": "092100"}, "312": {"name": "\u963f\u575d", "code": "092200"}, "313": {"name": "\u51c9\u5c71", "code": "092300"}, "314": {"name": "\u6d77\u5357\u7701", "code": "100000"}, "315": {"name": "\u6d77\u53e3", "code": "100200"}, "316": {"name": "\u4e09\u4e9a", "code": "100300"}, "317": {"name": "\u6d0b\u6d66\u7ecf\u6d4e\u5f00\u53d1\u533a", "code": "100400"}, "318": {"name": "\u6587\u660c", "code": "100500"}, "319": {"name": "\u743c\u6d77", "code": "100600"}, "320": {"name": "\u4e07\u5b81", "code": "100700"}, "321": {"name": "\u510b\u5dde", "code": "100800"}, "322": {"name": "\u4e1c\u65b9", "code": "100900"}, "323": {"name": "\u4e94\u6307\u5c71", "code": "101000"}, "324": {"name": "\u5b9a\u5b89", "code": "101100"}, "325": {"name": "\u5c6f\u660c", "code": "101200"}, "326": {"name": "\u6f84\u8fc8", "code": "101300"}, "327": {"name": "\u4e34\u9ad8", "code": "101400"}, "328": {"name": "\u4e09\u6c99", "code": "101500"}, "329": {"name": "\u743c\u4e2d", "code": "101600"}, "330": {"name": "\u4fdd\u4ead", "code": "101700"}, "331": {"name": "\u767d\u6c99", "code": "101800"}, "332": {"name": "\u660c\u6c5f", "code": "101900"}, "333": {"name": "\u4e50\u4e1c", "code": "102000"}, "334": {"name": "\u9675\u6c34", "code": "102100"}, "335": {"name": "\u798f\u5efa\u7701", "code": "110000"}, "336": {"name": "\u798f\u5dde", "code": "110200"}, "337": {"name": "\u9f13\u697c\u533a", "code": "110201"}, "338": {"name": "\u53f0\u6c5f\u533a", "code": "110202"}, "339": {"name": "\u4ed3\u5c71\u533a", "code": "110203"}, "340": {"name": "\u9a6c\u5c3e\u533a", "code": "110204"}, "341": {"name": "\u664b\u5b89\u533a", "code": "110205"}, "342": {"name": "\u95fd\u4faf\u53bf", "code": "110206"}, "343": {"name": "\u8fde\u6c5f\u53bf", "code": "110207"}, "344": {"name": "\u7f57\u6e90\u53bf", "code": "110208"}, "345": {"name": "\u95fd\u6e05\u53bf", "code": "110209"}, "346": {"name": "\u6c38\u6cf0\u53bf", "code": "110210"}, "347": {"name": "\u5e73\u6f6d\u53bf", "code": "110211"}, "348": {"name": "\u798f\u6e05\u5e02", "code": "110212"}, "349": {"name": "\u957f\u4e50\u5e02", "code": "110213"}, "350": {"name": "\u53a6\u95e8", "code": "110300"}, "351": {"name": "\u6cc9\u5dde", "code": "110400"}, "352": {"name": "\u6f33\u5dde", "code": "110500"}, "353": {"name": "\u8386\u7530", "code": "110600"}, "354": {"name": "\u4e09\u660e", "code": "110700"}, "355": {"name": "\u5357\u5e73", "code": "110800"}, "356": {"name": "\u5b81\u5fb7", "code": "110900"}, "357": {"name": "\u9f99\u5ca9", "code": "111000"}, "358": {"name": "\u5c71\u4e1c\u7701", "code": "120000"}, "359": {"name": "\u6d4e\u5357", "code": "120200"}, "360": {"name": "\u5386\u4e0b\u533a", "code": "120201"}, "361": {"name": "\u5e02\u4e2d\u533a", "code": "120202"}, "362": {"name": "\u69d0\u836b\u533a", "code": "120203"}, "363": {"name": "\u5929\u6865\u533a", "code": "120204"}, "364": {"name": "\u5386\u57ce\u533a", "code": "120205"}, "365": {"name": "\u957f\u6e05\u533a", "code": "120206"}, "366": {"name": "\u5e73\u9634\u53bf", "code": "120207"}, "367": {"name": "\u6d4e\u9633\u53bf", "code": "120208"}, "368": {"name": "\u5546\u6cb3\u53bf", "code": "120209"}, "369": {"name": "\u7ae0\u4e18\u533a", "code": "120210"}, "370": {"name": "\u9ad8\u65b0\u533a", "code": "120211"}, "371": {"name": "\u9752\u5c9b", "code": "120300"}, "372": {"name": "\u5e02\u5357\u533a", "code": "120301"}, "373": {"name": "\u5e02\u5317\u533a", "code": "120302"}, "374": {"name": "\u9ec4\u5c9b\u533a", "code": "120303"}, "375": {"name": "\u5d02\u5c71\u533a", "code": "120304"}, "376": {"name": "\u57ce\u9633\u533a", "code": "120305"}, "377": {"name": "\u674e\u6ca7\u533a", "code": "120306"}, "378": {"name": "\u80f6\u5dde\u5e02", "code": "120307"}, "379": {"name": "\u5373\u58a8\u533a", "code": "120308"}, "380": {"name": "\u5e73\u5ea6\u5e02", "code": "120309"}, "381": {"name": "\u83b1\u897f\u5e02", "code": "120310"}, "382": {"name": "\u70df\u53f0", "code": "120400"}, "383": {"name": "\u6f4d\u574a", "code": "120500"}, "384": {"name": "\u5a01\u6d77", "code": "120600"}, "385": {"name": "\u6dc4\u535a", "code": "120700"}, "386": {"name": "\u4e34\u6c82", "code": "120800"}, "387": {"name": "\u6d4e\u5b81", "code": "120900"}, "388": {"name": "\u4e1c\u8425", "code": "121000"}, "389": {"name": "\u6cf0\u5b89", "code": "121100"}, "390": {"name": "\u65e5\u7167", "code": "121200"}, "391": {"name": "\u5fb7\u5dde", "code": "121300"}, "392": {"name": "\u83cf\u6cfd", "code": "121400"}, "393": {"name": "\u6ee8\u5dde", "code": "121500"}, "394": {"name": "\u67a3\u5e84", "code": "121600"}, "395": {"name": "\u804a\u57ce", "code": "121700"}, "396": {"name": "\u83b1\u829c", "code": "121800"}, "397": {"name": "\u6c5f\u897f\u7701", "code": "130000"}, "398": {"name": "\u5357\u660c", "code": "130200"}, "399": {"name": "\u4e1c\u6e56\u533a", "code": "130201"}, "400": {"name": "\u897f\u6e56\u533a", "code": "130202"}, "401": {"name": "\u9752\u4e91\u8c31\u533a", "code": "130203"}, "402": {"name": "\u6e7e\u91cc\u533a", "code": "130204"}, "403": {"name": "\u9752\u5c71\u6e56\u533a", "code": "130205"}, "404": {"name": "\u5357\u660c\u53bf", "code": "130206"}, "405": {"name": "\u65b0\u5efa\u533a", "code": "130207"}, "406": {"name": "\u5b89\u4e49\u53bf", "code": "130208"}, "407": {"name": "\u8fdb\u8d24\u53bf", "code": "130209"}, "408": {"name": "\u7ea2\u8c37\u6ee9\u65b0\u533a", "code": "130210"}, "409": {"name": "\u4e5d\u6c5f", "code": "130300"}, "410": {"name": "\u666f\u5fb7\u9547", "code": "130400"}, "411": {"name": "\u840d\u4e61", "code": "130500"}, "412": {"name": "\u65b0\u4f59", "code": "130600"}, "413": {"name": "\u9e70\u6f6d", "code": "130700"}, "414": {"name": "\u8d63\u5dde", "code": "130800"}, "415": {"name": "\u5409\u5b89", "code": "130900"}, "416": {"name": "\u5b9c\u6625", "code": "131000"}, "417": {"name": "\u629a\u5dde", "code": "131100"}, "418": {"name": "\u4e0a\u9976", "code": "131200"}, "419": {"name": "\u5e7f\u897f", "code": "140000"}, "420": {"name": "\u5357\u5b81", "code": "140200"}, "421": {"name": "\u6842\u6797", "code": "140300"}, "422": {"name": "\u67f3\u5dde", "code": "140400"}, "423": {"name": "\u5317\u6d77", "code": "140500"}, "424": {"name": "\u7389\u6797", "code": "140600"}, "425": {"name": "\u68a7\u5dde", "code": "140700"}, "426": {"name": "\u9632\u57ce\u6e2f", "code": "140800"}, "427": {"name": "\u94a6\u5dde", "code": "140900"}, "428": {"name": "\u8d35\u6e2f", "code": "141000"}, "429": {"name": "\u767e\u8272", "code": "141100"}, "430": {"name": "\u6cb3\u6c60", "code": "141200"}, "431": {"name": "\u6765\u5bbe", "code": "141300"}, "432": {"name": "\u5d07\u5de6", "code": "141400"}, "433": {"name": "\u8d3a\u5dde", "code": "141500"}, "434": {"name": "\u5b89\u5fbd\u7701", "code": "150000"}, "435": {"name": "\u5408\u80a5", "code": "150200"}, "436": {"name": "\u7476\u6d77\u533a", "code": "150201"}, "437": {"name": "\u5e90\u9633\u533a", "code": "150202"}, "438": {"name": "\u8700\u5c71\u533a", "code": "150203"}, "439": {"name": "\u5305\u6cb3\u533a", "code": "150204"}, "440": {"name": "\u7ecf\u5f00\u533a", "code": "150205"}, "441": {"name": "\u6ee8\u6e56\u65b0\u533a", "code": "150206"}, "442": {"name": "\u65b0\u7ad9\u533a", "code": "150207"}, "443": {"name": "\u9ad8\u65b0\u533a", "code": "150208"}, "444": {"name": "\u653f\u52a1\u533a", "code": "150209"}, "445": {"name": "\u5317\u57ce\u65b0\u533a", "code": "150210"}, "446": {"name": "\u5de2\u6e56\u5e02", "code": "150211"}, "447": {"name": "\u957f\u4e30\u53bf", "code": "150212"}, "448": {"name": "\u80a5\u4e1c\u53bf", "code": "150213"}, "449": {"name": "\u80a5\u897f\u53bf", "code": "150214"}, "450": {"name": "\u5e90\u6c5f\u53bf", "code": "150215"}, "451": {"name": "\u829c\u6e56", "code": "150300"}, "452": {"name": "\u5b89\u5e86", "code": "150400"}, "453": {"name": "\u9a6c\u978d\u5c71", "code": "150500"}, "454": {"name": "\u868c\u57e0", "code": "150600"}, "455": {"name": "\u961c\u9633", "code": "150700"}, "456": {"name": "\u94dc\u9675", "code": "150800"}, "457": {"name": "\u6ec1\u5dde", "code": "150900"}, "458": {"name": "\u9ec4\u5c71", "code": "151000"}, "459": {"name": "\u6dee\u5357", "code": "151100"}, "460": {"name": "\u516d\u5b89", "code": "151200"}, "461": {"name": "\u5ba3\u57ce", "code": "151400"}, "462": {"name": "\u6c60\u5dde", "code": "151500"}, "463": {"name": "\u5bbf\u5dde", "code": "151600"}, "464": {"name": "\u6dee\u5317", "code": "151700"}, "465": {"name": "\u4eb3\u5dde", "code": "151800"}, "466": {"name": "\u6cb3\u5317\u7701", "code": "160000"}, "467": {"name": "\u96c4\u5b89\u65b0\u533a", "code": "160100"}, "468": {"name": "\u77f3\u5bb6\u5e84", "code": "160200"}, "469": {"name": "\u5eca\u574a", "code": "160300"}, "470": {"name": "\u4fdd\u5b9a", "code": "160400"}, "471": {"name": "\u5510\u5c71", "code": "160500"}, "472": {"name": "\u79e6\u7687\u5c9b", "code": "160600"}, "473": {"name": "\u90af\u90f8", "code": "160700"}, "474": {"name": "\u6ca7\u5dde", "code": "160800"}, "475": {"name": "\u5f20\u5bb6\u53e3", "code": "160900"}, "476": {"name": "\u627f\u5fb7", "code": "161000"}, "477": {"name": "\u90a2\u53f0", "code": "161100"}, "478": {"name": "\u8861\u6c34", "code": "161200"}, "479": {"name": "\u71d5\u90ca\u5f00\u53d1\u533a", "code": "161300"}, "480": {"name": "\u6cb3\u5357\u7701", "code": "170000"}, "481": {"name": "\u90d1\u5dde", "code": "170200"}, "482": {"name": "\u4e2d\u539f\u533a", "code": "170201"}, "483": {"name": "\u4e8c\u4e03\u533a", "code": "170202"}, "484": {"name": "\u7ba1\u57ce\u56de\u65cf\u533a", "code": "170203"}, "485": {"name": "\u91d1\u6c34\u533a", "code": "170204"}, "486": {"name": "\u4e0a\u8857\u533a", "code": "170205"}, "487": {"name": "\u60e0\u6d4e\u533a", "code": "170206"}, "488": {"name": "\u4e2d\u725f\u53bf", "code": "170207"}, "489": {"name": "\u5de9\u4e49\u5e02", "code": "170208"}, "490": {"name": "\u8365\u9633\u5e02", "code": "170209"}, "491": {"name": "\u65b0\u5bc6\u5e02", "code": "170210"}, "492": {"name": "\u65b0\u90d1\u5e02", "code": "170211"}, "493": {"name": "\u767b\u5c01\u5e02", "code": "170212"}, "494": {"name": "\u90d1\u4e1c\u65b0\u533a", "code": "170213"}, "495": {"name": "\u9ad8\u65b0\u533a", "code": "170214"}, "496": {"name": "\u7ecf\u5f00\u533a", "code": "170215"}, "497": {"name": "\u90d1\u5dde\u822a\u7a7a\u6e2f\u533a", "code": "170216"}, "498": {"name": "\u6d1b\u9633", "code": "170300"}, "499": {"name": "\u5f00\u5c01", "code": "170400"}, "500": {"name": "\u7126\u4f5c", "code": "170500"}, "501": {"name": "\u5357\u9633", "code": "170600"}, "502": {"name": "\u65b0\u4e61", "code": "170700"}, "503": {"name": "\u5468\u53e3", "code": "170800"}, "504": {"name": "\u5b89\u9633", "code": "170900"}, "505": {"name": "\u5e73\u9876\u5c71", "code": "171000"}, "506": {"name": "\u8bb8\u660c", "code": "171100"}, "507": {"name": "\u4fe1\u9633", "code": "171200"}, "508": {"name": "\u5546\u4e18", "code": "171300"}, "509": {"name": "\u9a7b\u9a6c\u5e97", "code": "171400"}, "510": {"name": "\u6f2f\u6cb3", "code": "171500"}, "511": {"name": "\u6fee\u9633", "code": "171600"}, "512": {"name": "\u9e64\u58c1", "code": "171700"}, "513": {"name": "\u4e09\u95e8\u5ce1", "code": "171800"}, "514": {"name": "\u6d4e\u6e90", "code": "171900"}, "515": {"name": "\u9093\u5dde", "code": "172000"}, "516": {"name": "\u6e56\u5317\u7701", "code": "180000"}, "517": {"name": "\u6b66\u6c49", "code": "180200"}, "518": {"name": "\u6c5f\u5cb8\u533a", "code": "180201"}, "519": {"name": "\u6c5f\u6c49\u533a", "code": "180202"}, "520": {"name": "~\u53e3\u533a", "code": "180203"}, "521": {"name": "\u6c49\u9633\u533a", "code": "180204"}, "522": {"name": "\u6b66\u660c\u533a", "code": "180205"}, "523": {"name": "\u9752\u5c71\u533a", "code": "180206"}, "524": {"name": "\u6d2a\u5c71\u533a", "code": "180207"}, "525": {"name": "\u4e1c\u897f\u6e56\u533a", "code": "180208"}, "526": {"name": "\u6c49\u5357\u533a", "code": "180209"}, "527": {"name": "\u8521\u7538\u533a", "code": "180210"}, "528": {"name": "\u6c5f\u590f\u533a", "code": "180211"}, "529": {"name": "\u9ec4\u9642\u533a", "code": "180212"}, "530": {"name": "\u65b0\u6d32\u533a", "code": "180213"}, "531": {"name": "\u6b66\u6c49\u7ecf\u6d4e\u5f00\u53d1\u533a", "code": "180214"}, "532": {"name": "\u4e1c\u6e56\u65b0\u6280\u672f\u4ea7\u4e1a\u5f00\u53d1\u533a", "code": "180215"}, "533": {"name": "\u5b9c\u660c", "code": "180300"}, "534": {"name": "\u9ec4\u77f3", "code": "180400"}, "535": {"name": "\u8944\u9633", "code": "180500"}, "536": {"name": "\u5341\u5830", "code": "180600"}, "537": {"name": "\u8346\u5dde", "code": "180700"}, "538": {"name": "\u8346\u95e8", "code": "180800"}, "539": {"name": "\u5b5d\u611f", "code": "180900"}, "540": {"name": "\u9102\u5dde", "code": "181000"}, "541": {"name": "\u9ec4\u5188", "code": "181100"}, "542": {"name": "\u968f\u5dde", "code": "181200"}, "543": {"name": "\u54b8\u5b81", "code": "181300"}, "544": {"name": "\u4ed9\u6843", "code": "181400"}, "545": {"name": "\u6f5c\u6c5f", "code": "181500"}, "546": {"name": "\u5929\u95e8", "code": "181600"}, "547": {"name": "\u795e\u519c\u67b6", "code": "181700"}, "548": {"name": "\u6069\u65bd", "code": "181800"}, "549": {"name": "\u6e56\u5357\u7701", "code": "190000"}, "550": {"name": "\u957f\u6c99", "code": "190200"}, "551": {"name": "\u8299\u84c9\u533a", "code": "190201"}, "552": {"name": "\u5929\u5fc3\u533a", "code": "190202"}, "553": {"name": "\u5cb3\u9e93\u533a", "code": "190203"}, "554": {"name": "\u5f00\u798f\u533a", "code": "190204"}, "555": {"name": "\u96e8\u82b1\u533a", "code": "190205"}, "556": {"name": "\u671b\u57ce\u533a", "code": "190206"}, "557": {"name": "\u957f\u6c99\u53bf", "code": "190207"}, "558": {"name": "\u5b81\u4e61\u53bf", "code": "190208"}, "559": {"name": "\u6d4f\u9633\u5e02", "code": "190209"}, "560": {"name": "\u682a\u6d32", "code": "190300"}, "561": {"name": "\u6e58\u6f6d", "code": "190400"}, "562": {"name": "\u8861\u9633", "code": "190500"}, "563": {"name": "\u5cb3\u9633", "code": "190600"}, "564": {"name": "\u5e38\u5fb7", "code": "190700"}, "565": {"name": "\u76ca\u9633", "code": "190800"}, "566": {"name": "\u90f4\u5dde", "code": "190900"}, "567": {"name": "\u90b5\u9633", "code": "191000"}, "568": {"name": "\u6000\u5316", "code": "191100"}, "569": {"name": "\u5a04\u5e95", "code": "191200"}, "570": {"name": "\u6c38\u5dde", "code": "191300"}, "571": {"name": "\u5f20\u5bb6\u754c", "code": "191400"}, "572": {"name": "\u6e58\u897f", "code": "191500"}, "573": {"name": "\u9655\u897f\u7701", "code": "200000"}, "574": {"name": "\u897f\u5b89", "code": "200200"}, "575": {"name": "\u83b2\u6e56\u533a", "code": "200201"}, "576": {"name": "\u65b0\u57ce\u533a", "code": "200202"}, "577": {"name": "\u7891\u6797\u533a", "code": "200203"}, "578": {"name": "\u705e\u6865\u533a", "code": "200204"}, "579": {"name": "\u672a\u592e\u533a", "code": "200205"}, "580": {"name": "\u96c1\u5854\u533a", "code": "200206"}, "581": {"name": "\u960e\u826f\u533a", "code": "200207"}, "582": {"name": "\u4e34\u6f7c\u533a", "code": "200208"}, "583": {"name": "\u957f\u5b89\u533a", "code": "200209"}, "584": {"name": "\u84dd\u7530\u53bf", "code": "200210"}, "585": {"name": "\u5468\u81f3\u53bf", "code": "200211"}, "586": {"name": "\u9091\u533a", "code": "200212"}, "587": {"name": "\u9ad8\u9675\u533a", "code": "200213"}, "588": {"name": "\u9ad8\u65b0\u6280\u672f\u4ea7\u4e1a\u5f00\u53d1\u533a", "code": "200214"}, "589": {"name": "\u7ecf\u6d4e\u6280\u672f\u5f00\u53d1\u533a", "code": "200215"}, "590": {"name": "\u66f2\u6c5f\u6587\u5316\u65b0\u533a", "code": "200216"}, "591": {"name": "\u54c4\u9119\u6001\u533a", "code": "200217"}, "592": {"name": "\u56fd\u5bb6\u6c11\u7528\u822a\u5929\u4ea7\u4e1a\u57fa\u5730", "code": "200218"}, "593": {"name": "\u897f\u54b8\u65b0\u533a", "code": "200219"}, "594": {"name": "\u897f\u5b89\u960e\u826f\u822a\u7a7a\u57fa\u5730", "code": "200220"}, "595": {"name": "\u897f\u5b89\u56fd\u9645\u6e2f\u52a1\u533a", "code": "200221"}, "596": {"name": "\u54b8\u9633", "code": "200300"}, "597": {"name": "\u5b9d\u9e21", "code": "200400"}, "598": {"name": "\u94dc\u5ddd", "code": "200500"}, "599": {"name": "\u5ef6\u5b89", "code": "200600"}, "600": {"name": "\u6e2d\u5357", "code": "200700"}, "601": {"name": "\u6986\u6797", "code": "200800"}, "602": {"name": "\u6c49\u4e2d", "code": "200900"}, "603": {"name": "\u5b89\u5eb7", "code": "201000"}, "604": {"name": "\u5546\u6d1b", "code": "201100"}, "605": {"name": "\u6768\u51cc", "code": "201200"}, "606": {"name": "\u5c71\u897f\u7701", "code": "210000"}, "607": {"name": "\u592a\u539f", "code": "210200"}, "608": {"name": "\u8fd0\u57ce", "code": "210300"}, "609": {"name": "\u5927\u540c", "code": "210400"}, "610": {"name": "\u4e34\u6c7e", "code": "210500"}, "611": {"name": "\u957f\u6cbb", "code": "210600"}, "612": {"name": "\u664b\u57ce", "code": "210700"}, "613": {"name": "\u9633\u6cc9", "code": "210800"}, "614": {"name": "\u6714\u5dde", "code": "210900"}, "615": {"name": "\u664b\u4e2d", "code": "211000"}, "616": {"name": "\u5ffb\u5dde", "code": "211100"}, "617": {"name": "\u5415\u6881", "code": "211200"}, "618": {"name": "\u9ed1\u9f99\u6c5f\u7701", "code": "220000"}, "619": {"name": "\u54c8\u5c14\u6ee8", "code": "220200"}, "620": {"name": "\u9053\u91cc\u533a", "code": "220201"}, "621": {"name": "\u5357\u5c97\u533a", "code": "220202"}, "622": {"name": "\u9053\u5916\u533a", "code": "220203"}, "623": {"name": "\u5e73\u623f\u533a", "code": "220204"}, "624": {"name": "\u677e\u5317\u533a", "code": "220205"}, "625": {"name": "\u9999\u574a\u533a", "code": "220206"}, "626": {"name": "\u547c\u5170\u533a", "code": "220207"}, "627": {"name": "\u963f\u57ce\u533a", "code": "220208"}, "628": {"name": "\u4f9d\u5170\u53bf", "code": "220209"}, "629": {"name": "\u65b9\u6b63\u53bf", "code": "220210"}, "630": {"name": "\u5bbe\u53bf", "code": "220211"}, "631": {"name": "\u5df4\u5f66\u53bf", "code": "220212"}, "632": {"name": "\u6728\u5170\u53bf", "code": "220213"}, "633": {"name": "\u901a\u6cb3\u53bf", "code": "220214"}, "634": {"name": "\u5ef6\u5bff\u53bf", "code": "220215"}, "635": {"name": "\u53cc\u57ce\u533a", "code": "220216"}, "636": {"name": "\u5c1a\u5fd7\u5e02", "code": "220217"}, "637": {"name": "\u4e94\u5e38\u5e02", "code": "220218"}, "638": {"name": "\u4f0a\u6625", "code": "220300"}, "639": {"name": "\u7ee5\u5316", "code": "220400"}, "640": {"name": "\u5927\u5e86", "code": "220500"}, "641": {"name": "\u9f50\u9f50\u54c8\u5c14", "code": "220600"}, "642": {"name": "\u7261\u4e39\u6c5f", "code": "220700"}, "643": {"name": "\u4f73\u6728\u65af", "code": "220800"}, "644": {"name": "\u9e21\u897f", "code": "220900"}, "645": {"name": "\u9e64\u5c97", "code": "221000"}, "646": {"name": "\u53cc\u9e2d\u5c71", "code": "221100"}, "647": {"name": "\u9ed1\u6cb3", "code": "221200"}, "648": {"name": "\u4e03\u53f0\u6cb3", "code": "221300"}, "649": {"name": "\u5927\u5174\u5b89\u5cad", "code": "221400"}, "650": {"name": "\u8fbd\u5b81\u7701", "code": "230000"}, "651": {"name": "\u6c88\u9633", "code": "230200"}, "652": {"name": "\u5927\u4e1c\u533a", "code": "230201"}, "653": {"name": "\u6d51\u5357\u533a", "code": "230202"}, "654": {"name": "\u5eb7\u5e73\u53bf", "code": "230203"}, "655": {"name": "\u548c\u5e73\u533a", "code": "230204"}, "656": {"name": "\u7687\u59d1\u533a", "code": "230205"}, "657": {"name": "\u6c88\u5317\u65b0\u533a", "code": "230206"}, "658": {"name": "\u6c88\u6cb3\u533a", "code": "230207"}, "659": {"name": "\u82cf\u5bb6\u5c6f\u533a", "code": "230208"}, "660": {"name": "\u94c1\u897f\u533a", "code": "230209"}, "661": {"name": "\u4e8e\u6d2a\u533a", "code": "230210"}, "662": {"name": "\u6cd5\u5e93\u53bf", "code": "230211"}, "663": {"name": "\u8fbd\u4e2d\u533a", "code": "230212"}, "664": {"name": "\u65b0\u6c11\u5e02", "code": "230213"}, "665": {"name": "\u5927\u8fde", "code": "230300"}, "666": {"name": "\u897f\u5c97\u533a", "code": "230301"}, "667": {"name": "\u4e2d\u5c71\u533a", "code": "230302"}, "668": {"name": "\u6c99\u6cb3\u53e3\u533a", "code": "230303"}, "669": {"name": "\u7518\u4e95\u5b50\u533a", "code": "230304"}, "670": {"name": "\u65c5\u987a\u53e3\u533a", "code": "230305"}, "671": {"name": "\u91d1\u5dde\u533a", "code": "230306"}, "672": {"name": "\u74e6\u623f\u5e97\u5e02", "code": "230307"}, "673": {"name": "\u666e\u5170\u5e97\u533a", "code": "230308"}, "674": {"name": "\u5e84\u6cb3\u5e02", "code": "230309"}, "675": {"name": "\u957f\u6d77\u53bf", "code": "230310"}, "676": {"name": "\u9ad8\u65b0\u56ed\u533a", "code": "230312"}, "677": {"name": "\u957f\u5174\u5c9b", "code": "230313"}, "678": {"name": "\u5927\u8fde\u4fdd\u7a0e\u533a", "code": "230314"}, "679": {"name": "\u978d\u5c71", "code": "230400"}, "680": {"name": "\u8425\u53e3", "code": "230500"}, "681": {"name": "\u629a\u987a", "code": "230600"}, "682": {"name": "\u9526\u5dde", "code": "230700"}, "683": {"name": "\u4e39\u4e1c", "code": "230800"}, "684": {"name": "\u846b\u82a6\u5c9b", "code": "230900"}, "685": {"name": "\u672c\u6eaa", "code": "231000"}, "686": {"name": "\u8fbd\u9633", "code": "231100"}, "687": {"name": "\u94c1\u5cad", "code": "231200"}, "688": {"name": "\u76d8\u9526", "code": "231300"}, "689": {"name": "\u671d\u9633", "code": "231400"}, "690": {"name": "\u961c\u65b0", "code": "231500"}, "691": {"name": "\u5409\u6797\u7701", "code": "240000"}, "692": {"name": "\u957f\u6625", "code": "240200"}, "693": {"name": "\u671d\u9633\u533a", "code": "240201"}, "694": {"name": "\u5357\u5173\u533a", "code": "240202"}, "695": {"name": "\u5bbd\u57ce\u533a", "code": "240203"}, "696": {"name": "\u4e8c\u9053\u533a", "code": "240204"}, "697": {"name": "\u7eff\u56ed\u533a", "code": "240205"}, "698": {"name": "\u53cc\u9633\u533a", "code": "240206"}, "699": {"name": "\u7ecf\u6d4e\u6280\u672f\u5f00\u53d1\u533a", "code": "240207"}, "700": {"name": "\u9ad8\u65b0\u6280\u672f\u4ea7\u4e1a\u5f00\u53d1\u533a", "code": "240208"}, "701": {"name": "\u51c0\u6708\u7ecf\u6d4e\u5f00\u53d1\u533a", "code": "240209"}, "702": {"name": "\u6c7d\u8f66\u4ea7\u4e1a\u5f00\u53d1\u533a", "code": "240210"}, "703": {"name": "\u6986\u6811\u5e02", "code": "240211"}, "704": {"name": "\u4e5d\u53f0\u533a", "code": "240212"}, "705": {"name": "\u5fb7\u60e0\u5e02", "code": "240213"}, "706": {"name": "\u519c\u5b89\u53bf", "code": "240214"}, "707": {"name": "\u5409\u6797", "code": "240300"}, "708": {"name": "\u8fbd\u6e90", "code": "240400"}, "709": {"name": "\u901a\u5316", "code": "240500"}, "710": {"name": "\u56db\u5e73", "code": "240600"}, "711": {"name": "\u677e\u539f", "code": "240700"}, "712": {"name": "\u5ef6\u5409", "code": "240800"}, "713": {"name": "\u767d\u5c71", "code": "240900"}, "714": {"name": "\u767d\u57ce", "code": "241000"}, "715": {"name": "\u5ef6\u8fb9", "code": "241100"}, "716": {"name": "\u4e91\u5357\u7701", "code": "250000"}, "717": {"name": "\u6606\u660e", "code": "250200"}, "718": {"name": "\u4e94\u534e\u533a", "code": "250201"}, "719": {"name": "\u76d8\u9f99\u533a", "code": "250202"}, "720": {"name": "\u5b98\u6e21\u533a", "code": "250203"}, "721": {"name": "\u897f\u5c71\u533a", "code": "250204"}, "722": {"name": "\u4e1c\u5ddd\u533a", "code": "250205"}, "723": {"name": "\u5448\u8d21\u533a", "code": "250206"}, "724": {"name": "\u664b\u5b81\u533a", "code": "250207"}, "725": {"name": "\u5bcc\u6c11\u53bf", "code": "250208"}, "726": {"name": "\u5b9c\u826f\u53bf", "code": "250209"}, "727": {"name": "\u77f3\u6797\u5f5d\u65cf\u81ea\u6cbb\u53bf", "code": "250210"}, "728": {"name": "\u5d69\u660e\u53bf", "code": "250211"}, "729": {"name": "\u7984\u529d\u53bf", "code": "250212"}, "730": {"name": "\u5bfb\u7538\u53bf", "code": "250213"}, "731": {"name": "\u5b89\u5b81\u5e02", "code": "250214"}, "732": {"name": "\u66f2\u9756", "code": "250300"}, "733": {"name": "\u7389\u6eaa", "code": "250400"}, "734": {"name": "\u5927\u7406", "code": "250500"}, "735": {"name": "\u4e3d\u6c5f", "code": "250600"}, "736": {"name": "\u7ea2\u6cb3\u5dde", "code": "251000"}, "737": {"name": "\u666e\u6d31", "code": "251100"}, "738": {"name": "\u4fdd\u5c71", "code": "251200"}, "739": {"name": "\u662d\u901a", "code": "251300"}, "740": {"name": "\u6587\u5c71", "code": "251400"}, "741": {"name": "\u897f\u53cc\u7248\u7eb3", "code": "251500"}, "742": {"name": "\u5fb7\u5b8f", "code": "251600"}, "743": {"name": "\u695a\u96c4", "code": "251700"}, "744": {"name": "\u4e34\u6ca7", "code": "251800"}, "745": {"name": "\u6012\u6c5f", "code": "251900"}, "746": {"name": "\u8fea\u5e86", "code": "252000"}, "747": {"name": "\u8d35\u5dde\u7701", "code": "260000"}, "748": {"name": "\u8d35\u9633", "code": "260200"}, "749": {"name": "\u9075\u4e49", "code": "260300"}, "750": {"name": "\u516d\u76d8\u6c34", "code": "260400"}, "751": {"name": "\u5b89\u987a", "code": "260500"}, "752": {"name": "\u94dc\u4ec1", "code": "260600"}, "753": {"name": "\u6bd5\u8282", "code": "260700"}, "754": {"name": "\u9ed4\u897f\u5357", "code": "260800"}, "755": {"name": "\u9ed4\u4e1c\u5357", "code": "260900"}, "756": {"name": "\u9ed4\u5357", "code": "261000"}, "757": {"name": "\u7518\u8083\u7701", "code": "270000"}, "758": {"name": "\u5170\u5dde", "code": "270200"}, "759": {"name": "\u91d1\u660c", "code": "270300"}, "760": {"name": "\u5609\u5cea\u5173", "code": "270400"}, "761": {"name": "\u9152\u6cc9", "code": "270500"}, "762": {"name": "\u5929\u6c34", "code": "270600"}, "763": {"name": "\u6b66\u5a01", "code": "270700"}, "764": {"name": "\u767d\u94f6", "code": "270800"}, "765": {"name": "\u5f20\u6396", "code": "270900"}, "766": {"name": "\u5e73\u51c9", "code": "271000"}, "767": {"name": "\u5b9a\u897f", "code": "271100"}, "768": {"name": "\u9647\u5357", "code": "271200"}, "769": {"name": "\u5e86\u9633", "code": "271300"}, "770": {"name": "\u4e34\u590f", "code": "271400"}, "771": {"name": "\u7518\u5357", "code": "271500"}, "772": {"name": "\u5185\u8499\u53e4", "code": "280000"}, "773": {"name": "\u547c\u548c\u6d69\u7279", "code": "280200"}, "774": {"name": "\u8d64\u5cf0", "code": "280300"}, "775": {"name": "\u5305\u5934", "code": "280400"}, "776": {"name": "\u901a\u8fbd", "code": "280700"}, "777": {"name": "\u9102\u5c14\u591a\u65af", "code": "280800"}, "778": {"name": "\u5df4\u5f66\u6dd6\u5c14", "code": "280900"}, "779": {"name": "\u4e4c\u6d77", "code": "281000"}, "780": {"name": "\u547c\u4f26\u8d1d\u5c14", "code": "281100"}, "781": {"name": "\u4e4c\u5170\u5bdf\u5e03", "code": "281200"}, "782": {"name": "\u5174\u5b89\u76df", "code": "281300"}, "783": {"name": "\u9521\u6797\u90ed\u52d2\u76df", "code": "281400"}, "784": {"name": "\u963f\u62c9\u5584\u76df", "code": "281500"}, "785": {"name": "\u5b81\u590f", "code": "290000"}, "786": {"name": "\u94f6\u5ddd", "code": "290200"}, "787": {"name": "\u5434\u5fe0", "code": "290300"}, "788": {"name": "\u4e2d\u536b", "code": "290400"}, "789": {"name": "\u77f3\u5634\u5c71", "code": "290500"}, "790": {"name": "\u56fa\u539f", "code": "290600"}, "791": {"name": "\u897f\u85cf", "code": "300000"}, "792": {"name": "\u62c9\u8428", "code": "300200"}, "793": {"name": "\u65e5\u5580\u5219", "code": "300300"}, "794": {"name": "\u6797\u829d", "code": "300400"}, "795": {"name": "\u5c71\u5357", "code": "300500"}, "796": {"name": "\u660c\u90fd", "code": "300600"}, "797": {"name": "\u90a3\u66f2", "code": "300700"}, "798": {"name": "\u963f\u91cc", "code": "300800"}, "799": {"name": "\u65b0\u7586", "code": "310000"}, "800": {"name": "\u4e4c\u9c81\u6728\u9f50", "code": "310200"}, "801": {"name": "\u514b\u62c9\u739b\u4f9d", "code": "310300"}, "802": {"name": "\u5580\u4ec0\u5730\u533a", "code": "310400"}, "803": {"name": "\u4f0a\u7281", "code": "310500"}, "804": {"name": "\u963f\u514b\u82cf", "code": "310600"}, "805": {"name": "\u54c8\u5bc6", "code": "310700"}, "806": {"name": "\u77f3\u6cb3\u5b50", "code": "310800"}, "807": {"name": "\u963f\u62c9\u5c14", "code": "310900"}, "808": {"name": "\u4e94\u5bb6\u6e20", "code": "311000"}, "809": {"name": "\u56fe\u6728\u8212\u514b", "code": "311100"}, "810": {"name": "\u660c\u5409", "code": "311200"}, "811": {"name": "\u963f\u52d2\u6cf0", "code": "311300"}, "812": {"name": "\u5410\u9c81\u756a", "code": "311400"}, "813": {"name": "\u5854\u57ce", "code": "311500"}, "814": {"name": "\u548c\u7530", "code": "311600"}, "815": {"name": "\u514b\u5b5c\u52d2\u82cf\u67ef\u5c14\u514b\u5b5c", "code": "311700"}, "816": {"name": "\u5df4\u97f3\u90ed\u695e", "code": "311800"}, "817": {"name": "\u535a\u5c14\u5854\u62c9", "code": "311900"}, "818": {"name": "\u9752\u6d77\u7701", "code": "320000"}, "819": {"name": "\u897f\u5b81", "code": "320200"}, "820": {"name": "\u6d77\u4e1c", "code": "320300"}, "821": {"name": "\u6d77\u897f", "code": "320400"}, "822": {"name": "\u6d77\u5317", "code": "320500"}, "823": {"name": "\u9ec4\u5357", "code": "320600"}, "824": {"name": "\u6d77\u5357", "code": "320700"}, "825": {"name": "\u679c\u6d1b", "code": "320800"}, "826": {"name": "\u7389\u6811", "code": "320900"}, "827": {"name": "\u9999\u6e2f", "code": "330000"}, "828": {"name": "\u6fb3\u95e8", "code": "340000"}, "829": {"name": "\u53f0\u6e7e", "code": "350000"}, "830": {"name": "\u56fd\u5916", "code": "360000"}, "831": {"name": "\u4e9a\u6d32", "code": "361000"}, "832": {"name": "\u65e5\u672c", "code": "361001"}, "833": {"name": "\u97e9\u56fd", "code": "361002"}, "834": {"name": "\u9a6c\u6765\u897f\u4e9a", "code": "361003"}, "835": {"name": "\u65b0\u52a0\u5761", "code": "361004"}, "836": {"name": "\u6cf0\u56fd", "code": "361005"}, "837": {"name": "\u83f2\u5f8b\u5bbe", "code": "361006"}, "838": {"name": "\u5370\u5ea6\u5c3c\u897f\u4e9a", "code": "361007"}, "839": {"name": "\u65af\u91cc\u5170\u5361", "code": "361008"}, "840": {"name": "\u5370\u5ea6", "code": "361009"}, "841": {"name": "\u7f05\u7538", "code": "361010"}, "842": {"name": "\u8d8a\u5357", "code": "361011"}, "843": {"name": "\u671d\u9c9c", "code": "361012"}, "844": {"name": "\u54c8\u8428\u514b\u65af\u5766", "code": "361013"}, "845": {"name": "\u4e4c\u5179\u522b\u514b\u65af\u5766", "code": "361014"}, "846": {"name": "\u4f0a\u6717", "code": "361015"}, "847": {"name": "\u4f0a\u62c9\u514b", "code": "361016"}, "848": {"name": "\u963f\u5bcc\u6c57", "code": "361017"}, "849": {"name": "\u5df4\u57fa\u65af\u5766", "code": "361018"}, "850": {"name": "\u571f\u8033\u5176", "code": "361019"}, "851": {"name": "\u79d1\u5a01\u7279", "code": "361020"}, "852": {"name": "\u6c99\u7279\u963f\u62c9\u4f2f", "code": "361021"}, "853": {"name": "\u8499\u53e4", "code": "361022"}, "854": {"name": "\u5b5f\u52a0\u62c9\u56fd", "code": "361023"}, "855": {"name": "\u6b27\u6d32", "code": "362000"}, "856": {"name": "\u82f1\u56fd", "code": "362001"}, "857": {"name": "\u6cd5\u56fd", "code": "362002"}, "858": {"name": "\u5fb7\u56fd", "code": "362003"}, "859": {"name": "\u610f\u5927\u5229", "code": "362004"}, "860": {"name": "\u897f\u73ed\u7259", "code": "362005"}, "861": {"name": "\u8461\u8404\u7259", "code": "362006"}, "862": {"name": "\u7231\u5c14\u5170", "code": "362007"}, "863": {"name": "\u6ce2\u5170", "code": "362008"}, "864": {"name": "\u632a\u5a01", "code": "362009"}, "865": {"name": "\u745e\u5178", "code": "362010"}, "866": {"name": "\u82ac\u5170", "code": "362011"}, "867": {"name": "\u5965\u5730\u5229", "code": "362012"}, "868": {"name": "\u4e4c\u514b\u5170", "code": "362013"}, "869": {"name": "\u767d\u4fc4\u7f57\u65af", "code": "362014"}, "870": {"name": "\u4fdd\u52a0\u5229\u4e9a", "code": "362015"}, "871": {"name": "\u7f57\u9a6c\u5c3c\u4e9a", "code": "362016"}, "872": {"name": "\u5308\u7259\u5229", "code": "362017"}, "873": {"name": "\u5e0c\u814a", "code": "362018"}, "874": {"name": "\u4fc4\u7f57\u65af", "code": "362019"}, "875": {"name": "\u745e\u58eb", "code": "362020"}, "876": {"name": "\u4e39\u9ea6", "code": "362021"}, "877": {"name": "\u6bd4\u5229\u65f6", "code": "362022"}, "878": {"name": "\u8377\u5170", "code": "362023"}, "879": {"name": "\u7f8e\u6d32", "code": "363000"}, "880": {"name": "\u7f8e\u56fd", "code": "363001"}, "881": {"name": "\u52a0\u62ff\u5927", "code": "363002"}, "882": {"name": "\u58a8\u897f\u54e5", "code": "363003"}, "883": {"name": "\u5df4\u897f", "code": "363004"}, "884": {"name": "\u963f\u6839\u5ef7", "code": "363005"}, "885": {"name": "\u667a\u5229", "code": "363006"}, "886": {"name": "\u79d8\u9c81", "code": "363007"}, "887": {"name": "\u54e5\u4f26\u6bd4\u4e9a", "code": "363008"}, "888": {"name": "\u59d4\u5185\u745e\u62c9", "code": "363009"}, "889": {"name": "\u73bb\u5229\u7ef4\u4e9a", "code": "363010"}, "890": {"name": "\u975e\u6d32", "code": "364000"}, "891": {"name": "\u57c3\u53ca", "code": "364001"}, "892": {"name": "\u5357\u975e", "code": "364002"}, "893": {"name": "\u82cf\u4e39", "code": "364003"}, "894": {"name": "\u963f\u5c14\u53ca\u5229\u4e9a", "code": "364004"}, "895": {"name": "\u57c3\u585e\u4fc4\u6bd4\u4e9a", "code": "364005"}, "896": {"name": "\u80af\u5c3c\u4e9a", "code": "364006"}, "897": {"name": "\u8d5e\u6bd4\u4e9a", "code": "364007"}, "898": {"name": "\u5766\u6851\u5c3c\u4e9a", "code": "364008"}, "899": {"name": "\u9a6c\u8fbe\u52a0\u65af\u52a0", "code": "364009"}, "900": {"name": "\u83ab\u6851\u6bd4\u514b", "code": "364010"}, "901": {"name": "\u5b89\u54e5\u62c9", "code": "364011"}, "902": {"name": "\u52a0\u7eb3", "code": "364012"}, "903": {"name": "\u6469\u6d1b\u54e5", "code": "364013"}, "904": {"name": "\u5c3c\u65e5\u5229\u4e9a", "code": "364014"}, "905": {"name": "\u5927\u6d0b\u6d32", "code": "365000"}, "906": {"name": "\u6fb3\u5927\u5229\u4e9a", "code": "365001"}, "907": {"name": "\u65b0\u897f\u5170", "code": "365002"}, "908": {"name": "\u5176\u4ed6", "code": "366000"}, "909": {"name": "\u73e0\u4e09\u89d2", "code": "01"}}}